hypernotes/__init__.py
hypernotes/__main__.py
hypernotes-2.0.2.dist-info/LICENSE
hypernotes-2.0.2.dist-info/METADATA
hypernotes-2.0.2.dist-info/WHEEL
hypernotes-2.0.2.dist-info/top_level.txt
hypernotes-2.0.2.dist-info/RECORD
