Metadata-Version: 2.1
Name: hypernotes
Version: 2.0.2
Summary: A lightweight Python package for taking notes on your machine learning experiments
Home-page: https://github.com/binste/hypernotes
Author: Stefan Binder
License: MIT
Keywords: machine learning,tracking,metrics,experiments,hyperparameters,model evaluation,data science
Platform: UNKNOWN
Classifier: Intended Audience :: Developers
Classifier: License :: OSI Approved :: MIT License
Classifier: Programming Language :: Python :: 3.6
Classifier: Programming Language :: Python :: 3.7
Classifier: Operating System :: OS Independent
Requires-Python: >=3.6
